noosphere/__main__.py
noosphere/__version__.py
noosphere/exceptions/__init__.py
noosphere/models/__init__.py
noosphere/models/graph_rules.py
noosphere/ports/__init__.py
noosphere/ports/cli/__init__.py
noosphere/ports/cli/main.py
noosphere/service/__init__.py
noosphere/service/neo4j_graph_service.py
tests/__init__.py
tests/config.yaml
tests/mock/example-text.md
noosphere_kg-0.2.0a0.dist-info/METADATA
noosphere_kg-0.2.0a0.dist-info/WHEEL
noosphere_kg-0.2.0a0.dist-info/entry_points.txt
noosphere_kg-0.2.0a0.dist-info/RECORD
