Metadata-Version: 2.3
Name: noosphere-kg
Version: 0.2.0a0
Summary: A simple tool to generate knowledge graphs from documents
License: Apache-2.0
Author: Samuel Galvão Elias
Author-email: sgelias@outlook.com
Requires-Python: >=3.12,<3.14
Classifier: License :: OSI Approved :: Apache Software License
Classifier: Programming Language :: Python :: 3
Classifier: Programming Language :: Python :: 3.12
Classifier: Programming Language :: Python :: 3.13
Requires-Dist: docling (>=2.48.0,<3.0.0)
Requires-Dist: langchain-community (>=0.3.29,<0.4.0)
Requires-Dist: langchain-experimental (>=0.3.4,<0.4.0)
Requires-Dist: langchain-neo4j (>=0.5.0,<0.6.0)
Requires-Dist: langchain-openai (>=0.3.32,<0.4.0)
Requires-Dist: neo4j (>=5.28.2,<6.0.0)
Requires-Dist: pydantic (>=2.11.7,<3.0.0)
Requires-Dist: pyyaml (>=6.0.2,<7.0.0)
Requires-Dist: rich-click (>=1.8.9,<2.0.0)
Requires-Dist: termcolor (>=3.1.0,<4.0.0)
Project-URL: Homepage, https://github.com/LepistaBio/noosphere
